LICENSE
README.md
setup.py
dag_craft/__init__.py
dag_craft/factory.py
dag_craft.egg-info/PKG-INFO
dag_craft.egg-info/SOURCES.txt
dag_craft.egg-info/dependency_links.txt
dag_craft.egg-info/requires.txt
dag_craft.egg-info/top_level.txt
dag_craft/models/__init__.py
dag_craft/models/task.py