Metadata-Version: 2.1
Name: dag-craft
Version: 0.0.4
Summary: Dag Factory para o Airflow
Home-page: https://github.com/MurilloSSJ/airflow-dag-factory
Author: Murillo Jacob
Author-email: murillostore@gmail.com
License: MIT License
Keywords: Airflow,DAG,Factory
License-File: LICENSE
